clouding_server_manager/__init__.py
clouding_server_manager/__main__.py
clouding_server_manager/commands.py
clouding_server_manager/constants.py
clouding_server_manager/helpers.py
clouding_server_manager-1.0.5.dist-info/LICENSE
clouding_server_manager-1.0.5.dist-info/METADATA
clouding_server_manager-1.0.5.dist-info/WHEEL
clouding_server_manager-1.0.5.dist-info/entry_points.txt
clouding_server_manager-1.0.5.dist-info/RECORD
