Metadata-Version: 2.1
Name: clouding-server-manager
Version: 1.0.5
Summary: A Python project to easily manage Clouding servers from the command line.
Author: dmarts05
Author-email: dmarts05@estudiantes.unileon.es
Requires-Python: >=3.9,<4.0
Classifier: Programming Language :: Python :: 3
Classifier: Programming Language :: Python :: 3.9
Classifier: Programming Language :: Python :: 3.10
Classifier: Programming Language :: Python :: 3.11
Requires-Dist: click (>=8.1.3,<9.0.0)
Requires-Dist: python-dotenv (>=1.0.0,<2.0.0)
Requires-Dist: requests (>=2.31.0,<3.0.0)
